dex/__init__.py
dex/aave.py
dex/aerodrome.py
dex/base.py
dex/config.py
dex/dex_manager.py
dex/erc20.py
dex/error_constants.py
dex/uniswap.py
dex/abis/aerodrome_factory_abi.json
dex/abis/aerodrome_pool_abi.json
dex/abis/aerodrome_quoter_abi.json
dex/abis/aerodrome_router_abi.json
dex/abis/atoken.json
dex/abis/erc20_abi.json
dex/abis/uniswap_factory_abi.json
dex/abis/uniswap_pool_abi.json
dex/abis/uniswap_quoter_abi.json
dex/abis/uniswap_router_abi.json
dex/abis/weth_abi.json
dexlib-0.1.7.dist-info/METADATA
dexlib-0.1.7.dist-info/WHEEL
dexlib-0.1.7.dist-info/top_level.txt
dexlib-0.1.7.dist-info/RECORD
